setup.py
cdn.egg-info/PKG-INFO
cdn.egg-info/SOURCES.txt
cdn.egg-info/dependency_links.txt
cdn.egg-info/requires.txt
cdn.egg-info/top_level.txt
settings/__init__.py
settings/base.py
settings/local.py
settings/prod.py