Metadata-Version: 1.1
Name: cdn
Version: 0.0.1
Summary: Content delivery application (In alpha! Please, don't use!)
Home-page: https://github.com/pirsipy/cdn
Author: Pirsipy
Author-email: dev@pirsipy.com
License: MIT
Keywords: cdn django content delivery application
Platform: UNKNOWN
Classifier: Environment :: Web Environment
Classifier: Intended Audience :: Developers
Classifier: License :: OSI Approved :: MIT License
Classifier: Operating System :: OS Independent
Classifier: Programming Language :: Python
Classifier: Topic :: Internet :: WWW/HTTP :: Dynamic Content
Classifier: Topic :: Software Development :: Libraries :: Python Modules
